setup.py
progress/__init__.py
progress/bar.py
progress/counter.py
progress/helpers.py
progress/spinner.py
progress.egg-info/PKG-INFO
progress.egg-info/SOURCES.txt
progress.egg-info/dependency_links.txt
progress.egg-info/top_level.txt