Metadata-Version: 1.0
Name: progress
Version: 1.0
Summary: Easy to use progress bars
Home-page: http://github.com/verigak/progress/
Author: Giorgos Verigakis
Author-email: verigak@gmail.com
License: ISC
Platform: UNKNOWN
Classifier: Environment :: Console
Classifier: Intended Audience :: Developers
Classifier: License :: OSI Approved :: ISC License (ISCL)
Classifier: Programming Language :: Python :: 2.6
Classifier: Programming Language :: Python :: 2.7
Classifier: Programming Language :: Python :: 3.3
